README.rst
setup.py
pyfm/__init__.py
pyfm/config.py
pyfm/douban.py
pyfm/fm.py
pyfm/notifier.py
pyfm/player.py
pyfm/scrobbler.py
pyfm/song.py
pyfm/ui.py
pyfm.egg-info/PKG-INFO
pyfm.egg-info/SOURCES.txt
pyfm.egg-info/dependency_links.txt
pyfm.egg-info/entry_points.txt
pyfm.egg-info/requires.txt
pyfm.egg-info/top_level.txt