Metadata-Version: 1.1
Name: pyfm
Version: 0.2.2
Summary: A Tiny and Smart Terminal Player of douban.fm 
Home-page: https://github.com/skyline75489/pyfm
Author: skyline75489
Author-email: skyline75489@outlook.com
License: MIT
Platform: UNKNOWN
Classifier: Environment :: Console
Classifier: Environment :: Console :: Curses
Classifier: Intended Audience :: End Users/Desktop
Classifier: License :: OSI Approved :: MIT License
Classifier: Natural Language :: Chinese (Simplified)
Classifier: Operating System :: MacOS :: MacOS X
Classifier: Operating System :: POSIX
Classifier: Operating System :: Unix
Classifier: Programming Language :: Python :: 2
Classifier: Programming Language :: Python :: 2.7
Classifier: Programming Language :: Python :: 3.4
Classifier: Topic :: Multimedia :: Sound/Audio :: Players
